README.md
setup.py
modeloss/__init__.py
modeloss/pytorch.py
modeloss/tf.py
modeloss.egg-info/PKG-INFO
modeloss.egg-info/SOURCES.txt
modeloss.egg-info/dependency_links.txt
modeloss.egg-info/requires.txt
modeloss.egg-info/top_level.txt