Metadata-Version: 1.2
Name: modeloss
Version: 0.1.0
Summary: Moment Decorrelation for constrained NN outputs with respect to protected attributes. (Decorrelated (flat), linear, quadratic, etc.)
Home-page: https://github.com/okitouni/MoDe
Author: Ouail Kitouni
Author-email: kitouni@gmail.com
License: BSD 2-clause
Platform: UNKNOWN
Requires-Python: >=3.6
